vandermonde/__about__.py
vandermonde/__init__.py
vandermonde/main.py
vandermonde-0.1.3.dist-info/LICENSE
vandermonde-0.1.3.dist-info/METADATA
vandermonde-0.1.3.dist-info/WHEEL
vandermonde-0.1.3.dist-info/top_level.txt
vandermonde-0.1.3.dist-info/RECORD
