Metadata-Version: 2.1
Name: vandermonde
Version: 0.1.3
Summary: Vandermonde matrix tools
Home-page: https://github.com/nschloe/vandermonde
Author: Nico Schlömer
Author-email: nico.schloemer@gmail.com
License: MIT
Project-URL: Code, https://github.com/nschloe/vandermonde
Project-URL: Issues, https://github.com/nschloe/vandermonde/issues
Platform: UNKNOWN
Classifier: Development Status :: 4 - Beta
Classifier: Intended Audience :: Science/Research
Classifier: License :: OSI Approved :: MIT License
Classifier: Operating System :: OS Independent
Classifier: Programming Language :: Python
Classifier: Programming Language :: Python :: 3
Classifier: Programming Language :: Python :: 3.6
Classifier: Programming Language :: Python :: 3.7
Classifier: Programming Language :: Python :: 3.8
Classifier: Programming Language :: Python :: 3.9
Classifier: Topic :: Scientific/Engineering
Classifier: Topic :: Scientific/Engineering :: Mathematics
Requires-Python: >=3.6
Requires-Dist: numpy
Requires-Dist: importlib-metadata ; python_version < "3.8"
